profile_config/__init__.py
profile_config/discovery.py
profile_config/exceptions.py
profile_config/loader.py
profile_config/merger.py
profile_config/profiles.py
profile_config/resolver.py
profile_config/tests/__init__.py
profile_config/tests/test_discovery.py
profile_config/tests/test_env_expansion.py
profile_config/tests/test_env_vars.py
profile_config/tests/test_flexible_overrides.py
profile_config/tests/test_profile_filename.py
profile_config/tests/test_profiles.py
profile_config/tests/test_resolver.py
profile_config/tests/test_toml_support.py
profile_config-1.3.2.dist-info/licenses/LICENSE
profile_config-1.3.2.dist-info/METADATA
profile_config-1.3.2.dist-info/WHEEL
profile_config-1.3.2.dist-info/top_level.txt
profile_config-1.3.2.dist-info/RECORD
