Metadata-Version: 2.4
Name: profile-config
Version: 1.3.2
Summary: A Python library for managing hierarchical configuration files with profile-based inheritance and variable interpolation
Author-email: Profile Config Contributors <martin.j.bartlett@gmail.com>
License: MIT
Project-URL: Homepage, https://github.com/bassmanitram/profile-config
Project-URL: Documentation, https://bassmanitram.github.io/profile-config/
Project-URL: Repository, https://github.com/bassmanitram/profile-config.git
Project-URL: Bug Tracker, https://github.com/bassmanitram/profile-config/issues
Keywords: config,configuration,profiles,yaml,json,toml,inheritance,interpolation
Classifier: Development Status :: 5 - Production/Stable
Classifier: Intended Audience :: Developers
Classifier: License :: OSI Approved :: MIT License
Classifier: Operating System :: OS Independent
Classifier: Programming Language :: Python :: 3
Classifier: Programming Language :: Python :: 3.8
Classifier: Programming Language :: Python :: 3.9
Classifier: Programming Language :: Python :: 3.10
Classifier: Programming Language :: Python :: 3.11
Classifier: Programming Language :: Python :: 3.12
Classifier: Topic :: Software Development :: Libraries :: Python Modules
Classifier: Topic :: System :: Systems Administration
Classifier: Topic :: Utilities
Requires-Python: >=3.8
License-File: LICENSE
Requires-Dist: omegaconf>=2.3.0
Requires-Dist: pyyaml>=6.0
Provides-Extra: toml
Requires-Dist: tomli>=2.0.0; python_version < "3.11" and extra == "toml"
Provides-Extra: test
Requires-Dist: pytest>=6.0; extra == "test"
Requires-Dist: pytest-cov>=3.0.0; extra == "test"
Provides-Extra: dev
Requires-Dist: black>=22.0.0; extra == "dev"
Requires-Dist: isort>=5.0.0; extra == "dev"
Requires-Dist: flake8>=4.0.0; extra == "dev"
Requires-Dist: mypy>=0.991; extra == "dev"
Requires-Dist: build>=0.8.0; extra == "dev"
Requires-Dist: pre-commit>=3.0.0; extra == "dev"
Requires-Dist: bandit>=1.7.0; extra == "dev"
Requires-Dist: types-PyYAML>=6.0.0; extra == "dev"
Dynamic: license-file
